pyfiji/__init__.py
pyfiji/methods.py
pyfiji-1.0.0.dist-info/METADATA
pyfiji-1.0.0.dist-info/WHEEL
pyfiji-1.0.0.dist-info/top_level.txt
pyfiji-1.0.0.dist-info/RECORD
