Metadata-Version: 2.1
Name: pyfiji
Version: 1.0.0
Summary: Python scripts as precursor to Fiji plugins
Home-page: https://github.com/kapoorlab/pyfiji/
Author: Varun Kapoor
Author-email: randomaccessiblekapoor@gmail.com
License: UNKNOWN
Platform: UNKNOWN
Classifier: Development Status :: 3 - Alpha
Classifier: Natural Language :: English
Classifier: License :: OSI Approved :: MIT License
Classifier: Operating System :: OS Independent
Classifier: Programming Language :: Python
Classifier: Programming Language :: Python :: 3.9
Requires-Dist: pandas
Requires-Dist: numpy
Requires-Dist: scipy
Requires-Dist: tifffile
Requires-Dist: matplotlib
Requires-Dist: opencv-python
